cma/__init__.py
cma/core.py
cma/core_test.py
cma_es-1.5.0.dist-info/LICENSE
cma_es-1.5.0.dist-info/METADATA
cma_es-1.5.0.dist-info/WHEEL
cma_es-1.5.0.dist-info/top_level.txt
cma_es-1.5.0.dist-info/RECORD
